dora_lakehouse_aws/__init__.py
dora_lakehouse_aws-0.0.1.dist-info/LICENSE
dora_lakehouse_aws-0.0.1.dist-info/WHEEL
dora_lakehouse_aws-0.0.1.dist-info/METADATA
dora_lakehouse_aws-0.0.1.dist-info/RECORD
